netbox_changelog_diff_plugin/__init__.py
netbox_changelog_diff_plugin/filtersets.py
netbox_changelog_diff_plugin/forms.py
netbox_changelog_diff_plugin/models.py
netbox_changelog_diff_plugin/navigation.py
netbox_changelog_diff_plugin/tables.py
netbox_changelog_diff_plugin/template_content.py
netbox_changelog_diff_plugin/urls.py
netbox_changelog_diff_plugin/utils.py
netbox_changelog_diff_plugin/views.py
netbox_changelog_diff_plugin/templates/netbox_changelog_diff_plugin/changelogdiff.html
netbox_changelog_diff_plugin/utilities/html_differ.py
netbox_changelog_diff_plugin-0.2.1.dist-info/LICENSE
netbox_changelog_diff_plugin-0.2.1.dist-info/METADATA
netbox_changelog_diff_plugin-0.2.1.dist-info/WHEEL
netbox_changelog_diff_plugin-0.2.1.dist-info/top_level.txt
netbox_changelog_diff_plugin-0.2.1.dist-info/RECORD
