Metadata-Version: 2.1
Name: netbox-changelog-diff-plugin
Version: 0.2.1
Summary: NetBox plugin for more detailed changlog diffs
Author-email: Jamie Murphy <git@jam.ie>
Project-URL: Documentation, https://github.com/ITJamie/netbox-changelog-diff-plugin/blob/main/README.md
Project-URL: Source, https://github.com/ITJamie/netbox-changelog-diff-plugin
Project-URL: Tracker, https://github.com/ITJamie/netbox-changelog-diff-plugin/issues
Classifier: Development Status :: 3 - Alpha
Classifier: Intended Audience :: Developers
Classifier: Natural Language :: English
Classifier: Programming Language :: Python :: 3 :: Only
Classifier: Programming Language :: Python :: 3.10
Classifier: Programming Language :: Python :: 3.11
Classifier: Programming Language :: Python :: 3.12
Requires-Python: >=3.10.0
License-File: LICENSE
Provides-Extra: test
Requires-Dist: black ==24.3.0 ; extra == 'test'
Requires-Dist: check-manifest ==0.49 ; extra == 'test'
Requires-Dist: flake8 ; extra == 'test'
Requires-Dist: flake8-pyproject ; extra == 'test'
Requires-Dist: pre-commit ==3.7.0 ; extra == 'test'
Requires-Dist: pytest ==8.1.1 ; extra == 'test'
